README.md
setup.py
bin/sequence-client
bin/sequence-server
pbes/__init__.py
pbes/clientside.py
pbes/sequense_pb2.py
pbes/sequense_pb2_grpc.py
pbes/serverside.py
seqence_server_demo.egg-info/PKG-INFO
seqence_server_demo.egg-info/SOURCES.txt
seqence_server_demo.egg-info/dependency_links.txt
seqence_server_demo.egg-info/requires.txt
seqence_server_demo.egg-info/top_level.txt