Metadata-Version: 1.2
Name: seqence-server-demo
Version: 0.0.1
Summary: seqence-server-demo
Home-page: https://github.com/Neeky/protobuf-es
Author: Neeky
Author-email: neeky@live.com
Maintainer: Neeky
Maintainer-email: neeky@live.com
License: UNKNOWN
Platform: UNKNOWN
Classifier: Development Status :: 4 - Beta
Classifier: Intended Audience :: Developers
Classifier: Operating System :: POSIX
Classifier: Operating System :: MacOS :: MacOS X
Classifier: Programming Language :: Python :: 3.6
Classifier: Programming Language :: Python :: 3.7
Classifier: Programming Language :: Python :: 3.8
Requires-Python: >=3.8.*
